aiokonstsmide/__init__.py
aiokonstsmide/codec.py
aiokonstsmide/device.py
aiokonstsmide/exceptions.py
aiokonstsmide/message.py
aiokonstsmide/scanner.py
aiokonstsmide-0.2.1.dist-info/METADATA
aiokonstsmide-0.2.1.dist-info/WHEEL
aiokonstsmide-0.2.1.dist-info/licenses/LICENSE
aiokonstsmide-0.2.1.dist-info/RECORD
